rotest/__init__.py
rotest/api/__init__.py
rotest/api/consumers.py
rotest/api/request_token.py
rotest/api/urls.py
rotest/api/common/__init__.py
rotest/api/common/models.py
rotest/api/common/responses.py
rotest/api/resource_control/__init__.py
rotest/api/resource_control/cleanup_user.py
rotest/api/resource_control/lock_resources.py
rotest/api/resource_control/query_resources.py
rotest/api/resource_control/release_resources.py
rotest/api/resource_control/update_fields.py
rotest/api/signature_control/__init__.py
rotest/api/signature_control/get_or_create.py
rotest/api/test_control/__init__.py
rotest/api/test_control/add_test_result.py
rotest/api/test_control/get_statistics.py
rotest/api/test_control/middleware.py
rotest/api/test_control/should_skip.py
rotest/api/test_control/start_composite.py
rotest/api/test_control/start_test.py
rotest/api/test_control/start_test_run.py
rotest/api/test_control/stop_composite.py
rotest/api/test_control/stop_test.py
rotest/api/test_control/update_resources.py
rotest/api/test_control/update_run_data.py
rotest/cli/__init__.py
rotest/cli/client.py
rotest/cli/discover.py
rotest/cli/main.py
rotest/cli/server.py
rotest/common/__init__.py
rotest/common/config.py
rotest/common/constants.py
rotest/common/default_config.json
rotest/common/log.py
rotest/common/schema.json
rotest/common/utils.py
rotest/common/django_utils/__init__.py
rotest/common/django_utils/common.py
rotest/common/django_utils/fields.py
rotest/common/django_utils/routing.py
rotest/common/django_utils/settings.py
rotest/common/django_utils/urls.py
rotest/common/django_utils/fixtures/__init__.py
rotest/common/django_utils/fixtures/case_ut.json
rotest/common/django_utils/fixtures/initial_data.json
rotest/common/django_utils/fixtures/resource_ut.json
rotest/common/django_utils/fixtures/signature_ut.json
rotest/common/django_utils/static/__init__.py
rotest/common/django_utils/static/style.css
rotest/core/__init__.py
rotest/core/abstract_test.py
rotest/core/admin.py
rotest-8.3.1.dist-info/LICENSE
rotest-8.3.1.dist-info/METADATA
rotest-8.3.1.dist-info/WHEEL
rotest-8.3.1.dist-info/entry_points.txt
rotest-8.3.1.dist-info/top_level.txt
rotest-8.3.1.dist-info/RECORD
