Metadata-Version: 2.1
Name: rotest
Version: 8.3.1
Summary: Resource oriented testing framework
Home-page: https://github.com/gregoil/rotest
Author: gregoil
Author-email: gregoil@walla.co.il
License: MIT
Keywords: testing system django unittest
Platform: UNKNOWN
Classifier: License :: OSI Approved :: MIT License
Classifier: Topic :: Software Development :: Testing
Classifier: Intended Audience :: Developers
Classifier: Programming Language :: Python :: 2
Classifier: Programming Language :: Python :: 2.7
Classifier: Programming Language :: Python :: 3
Classifier: Programming Language :: Python :: 3.6
Classifier: Programming Language :: Python :: 3.7
Classifier: Framework :: Django
Classifier: Framework :: Django :: 1.8
Classifier: Framework :: Django :: 1.9
Classifier: Framework :: Django :: 1.10
Classifier: Framework :: Django :: 1.11
Classifier: Framework :: Django :: 2.0
Classifier: Operating System :: Microsoft :: Windows
Classifier: Operating System :: POSIX
Classifier: Operating System :: Unix
Classifier: Operating System :: MacOS
Requires-Python: >=2.7,!=3.0.*,!=3.1.*,!=3.2.*,!=3.3.*,!=3.4.*,!=3.5.*
Requires-Dist: django (<2.1,>=1.8)
Requires-Dist: py
Requires-Dist: ipdbugger (>=2.5)
Requires-Dist: xlwt
Requires-Dist: attrdict
Requires-Dist: pyyaml
Requires-Dist: psutil
Requires-Dist: colorama
Requires-Dist: termcolor
Requires-Dist: jsonschema
Requires-Dist: basicstruct
Requires-Dist: future
Requires-Dist: swaggapi (>=0.6.7)
Requires-Dist: cached-property
Requires-Dist: channels (<2,>=1)
Requires-Dist: websocket-client (>=0.56)
Requires-Dist: statistics ; python_version=="2.7"
Provides-Extra: dev
Requires-Dist: pytest ; extra == 'dev'
Requires-Dist: pytest-django ; extra == 'dev'
Requires-Dist: pytest-cov ; extra == 'dev'
Requires-Dist: mock ; extra == 'dev'
Requires-Dist: pyfakefs ; extra == 'dev'
Requires-Dist: xlrd ; extra == 'dev'
Requires-Dist: pathlib2 ; extra == 'dev'
Requires-Dist: flake8 ; extra == 'dev'
Requires-Dist: pylint (<2.4) ; extra == 'dev'
Requires-Dist: waiting ; extra == 'dev'
